diff_highlight.py
diff_highlight-1.2.0.dist-info/DESCRIPTION.rst
diff_highlight-1.2.0.dist-info/METADATA
diff_highlight-1.2.0.dist-info/RECORD
diff_highlight-1.2.0.dist-info/WHEEL
diff_highlight-1.2.0.dist-info/entry_points.txt
diff_highlight-1.2.0.dist-info/metadata.json
diff_highlight-1.2.0.dist-info/top_level.txt
highlights/__init__.py
highlights/command.py
highlights/pprint.py
