Metadata-Version: 2.0
Name: diff-highlight
Version: 1.2.0
Summary: pretty diff highlighter; emphasis changed words in diff
Home-page: https://github.com/tk0miya/diff-highlight
Author: Takeshi Komiya
Author-email: i.tkomiya at gmail.com
License: Apache License 2.0
Keywords: mercurial,git,diff,highlight
Platform: UNKNOWN
Classifier: Development Status :: 5 - Production/Stable
Classifier: Intended Audience :: System Administrators
Classifier: License :: OSI Approved :: Apache Software License
Classifier: Programming Language :: Python
Classifier: Programming Language :: Python :: 2.6
Classifier: Programming Language :: Python :: 2.7
Classifier: Programming Language :: Python :: 3.2
Classifier: Programming Language :: Python :: 3.3
Classifier: Programming Language :: Python :: 3.4
Classifier: Programming Language :: Python :: 3.5
Classifier: Topic :: Software Development
Classifier: Topic :: Software Development :: Version Control
Classifier: Topic :: Text Processing :: Filters
Provides-Extra: testing
Requires-Dist: flake8; extra == 'testing'
Requires-Dist: mercurial; extra == 'testing'
Requires-Dist: mock; extra == 'testing'
Requires-Dist: nose; extra == 'testing'
Requires-Dist: six; extra == 'testing'
